enczoo/__init__.py
enczoo/base.py
enczoo/classic/__init__.py
enczoo/classic/pixels.py
enczoo/neural_networks/__init__.py
enczoo/neural_networks/base.py
enczoo/neural_networks/pretrained.py
enczoo/neural_networks/tests/__init__.py
enczoo/neural_networks/tests/test_pretrained_nn.py
enczoo/py.typed
enczoo/transforms/__init__.py
enczoo/transforms/random_projection.py
enczoo/utils.py
enczoo-0.1.1.dist-info/WHEEL
enczoo-0.1.1.dist-info/METADATA
enczoo-0.1.1.dist-info/RECORD
