Metadata-Version: 2.3
Name: enczoo
Version: 0.1.1
Summary: Map images (as `PIL.Images`) to intermediate representations (as `np.ndarray`) from off-the-shelf vision models.
Author: himjl
Author-email: himjl <mil@mit.edu>
License: MIT License
Requires-Dist: pillow>=12.1.0
Requires-Dist: torch>=2.9.1
Requires-Dist: torchvision>=0.24.1
Requires-Python: >=3.12
